seerapi_models/__init__.py
seerapi_models/_utils.py
seerapi_models/achievement.py
seerapi_models/battle_effect.py
seerapi_models/build_model/__init__.py
seerapi_models/common.py
seerapi_models/effect.py
seerapi_models/element_type.py
seerapi_models/items/__init__.py
seerapi_models/items/_common.py
seerapi_models/items/enegry_bead.py
seerapi_models/items/equip.py
seerapi_models/items/mintmark_gem.py
seerapi_models/items/skill_activation_item.py
seerapi_models/items/skill_stone.py
seerapi_models/metadata.py
seerapi_models/mintmark.py
seerapi_models/nature.py
seerapi_models/peak_pool.py
seerapi_models/pet/__init__.py
seerapi_models/pet/pet.py
seerapi_models/pet/pet_skin.py
seerapi_models/pet/petbook.py
seerapi_models/pet/soulmark.py
seerapi_models/skill.py
seerapi_models-103.2.0.dist-info/WHEEL
seerapi_models-103.2.0.dist-info/METADATA
seerapi_models-103.2.0.dist-info/RECORD
