Metadata-Version: 2.3
Name: seerapi-models
Version: 103.2.0
Summary: SeerAPI 数据模型/ORM 定义
Keywords: seerapi,models,orm
Author: Nattsu39
Author-email: Nattsu39 <Nattsu39@outlook.com>
License: MIT License
Classifier: Operating System :: OS Independent
Classifier: Intended Audience :: Developers
Classifier: License :: OSI Approved :: MIT License
Classifier: Programming Language :: Python :: 3.10
Classifier: Programming Language :: Python :: 3.11
Classifier: Programming Language :: Python :: 3.12
Classifier: Programming Language :: Python :: 3.13
Classifier: Programming Language :: Python :: 3.14
Requires-Dist: pydantic>=2.11.7,<2.12
Requires-Dist: sqlmodel>=0.0.27
Requires-Python: >=3.10
Project-URL: Homepage, https://github.com/SeerAPI/seerapi-models
Project-URL: Repository, https://github.com/SeerAPI/seerapi-models
